MHPKMS_client/__init__.py
MHPKMS-1.0.0.2.dist-info/METADATA
MHPKMS-1.0.0.2.dist-info/WHEEL
MHPKMS-1.0.0.2.dist-info/top_level.txt
MHPKMS-1.0.0.2.dist-info/RECORD
