Metadata-Version: 2.1
Name: MHPKMS
Version: 1.0.0.2
Summary: Send trial products take easy.
Home-page: https://github.com/MHP0920/MHPKMS
Author: MHP
Author-email: py.hacker.hieu@gmail.com
License: CC BY-ND 4.0
Keywords: MHP,KMS,trial,python,python3
Classifier: Programming Language :: Python :: 3
Classifier: License :: Free To Use But Restricted
Classifier: Operating System :: OS Independent
Requires-Python: >=3.6
Requires-Dist: requests
